weather_tui/__init__.py
weather_tui/__main__.py
weather_tui/app.py
weather_tui/models/__init__.py
weather_tui/models/forecast.py
weather_tui/screens/__init__.py
weather_tui/screens/search.py
weather_tui/screens/weather.py
weather_tui/services/__init__.py
weather_tui/services/geocoding.py
weather_tui/services/weather.py
weather_tui/utils/__init__.py
weather_tui/utils/colors.py
weather_tui/widgets/__init__.py
weather_tui/widgets/current_weather.py
weather_tui/widgets/daily_forecast.py
weather_tui/widgets/hourly_graph.py
weather_tui-1.4.0.dist-info/METADATA
weather_tui-1.4.0.dist-info/WHEEL
weather_tui-1.4.0.dist-info/entry_points.txt
weather_tui-1.4.0.dist-info/licenses/LICENSE
weather_tui-1.4.0.dist-info/RECORD
