Metadata-Version: 2.4
Name: weather-tui
Version: 1.4.0
Summary: A TUI application for displaying weather forecasts with hour-by-hour graphs
Project-URL: Homepage, https://github.com/benedikt-mayer/weather-tui
Project-URL: Repository, https://github.com/benedikt-mayer/weather-tui
Project-URL: Issues, https://github.com/benedikt-mayer/weather-tui/issues
Author-email: Benedikt Mayer <benedikt_mayer@outlook.de>
License: MIT
License-File: LICENSE
Keywords: forecast,terminal,textual,tui,weather
Classifier: Development Status :: 5 - Production/Stable
Classifier: Environment :: Console
Classifier: Intended Audience :: End Users/Desktop
Classifier: License :: OSI Approved :: MIT License
Classifier: Operating System :: OS Independent
Classifier: Programming Language :: Python :: 3
Classifier: Programming Language :: Python :: 3.12
Classifier: Topic :: Utilities
Requires-Python: >=3.12
Requires-Dist: httpx>=0.27.0
Requires-Dist: numpy>=2.4.0
Requires-Dist: openmeteo-requests>=1.2.0
Requires-Dist: python-dotenv>=1.0.0
Requires-Dist: textual-plotext>=1.0.1
Requires-Dist: textual>=0.47.0
Provides-Extra: dev
Requires-Dist: pytest-asyncio>=0.23.0; extra == 'dev'
Requires-Dist: pytest>=8.0.0; extra == 'dev'
Requires-Dist: ruff>=0.4.0; extra == 'dev'
Requires-Dist: textual-dev>=1.4.0; extra == 'dev'
